[
  {
    "Id": 4,
    "Title": "خدمات مو",
    "Description": "",
    "CoverImagePath": "d68c296b-0e54-4652-9bdd-851907b6ad0c@hair-service.webp"
  },
  {
    "Id":5,
    "Title": "خدمات ناخن",
    "Description": "",
    "CoverImagePath": "d68c296b-0e54-4652-9bdd-851907b6ad0c@nail-service.webp"
  },
  {
    "Id": 6,
    "Title": "خدمات پوست",
    "Description": "",
    "CoverImagePath": "d68c296b-0e54-4652-9bdd-851907b6ad0c@facial.webp"
  },
  {
    "Id": 7,
    "Title": "خدمات ابرو و مژه",
    "Description": "",
    "CoverImagePath": "d68c296b-0e54-4652-9bdd-851907b6ad0c@eyebrow-eyelash-service.webp"
  },
  {
    "Id": 8,
    "Title": "آرایش و میکاپ",
    "Description": "",
    "CoverImagePath": "d68c296b-0e54-4652-9bdd-851907b6ad0c@makeup.webp"
  }
]